TOPSIS_Mitul_101803084.py
TOPSIS_Mitul_101803084-0.0.2.dist-info/LICENSE.txt
TOPSIS_Mitul_101803084-0.0.2.dist-info/METADATA
TOPSIS_Mitul_101803084-0.0.2.dist-info/WHEEL
TOPSIS_Mitul_101803084-0.0.2.dist-info/top_level.txt
TOPSIS_Mitul_101803084-0.0.2.dist-info/RECORD
