Metadata-Version: 2.1
Name: TOPSIS-Mitul-101803084
Version: 0.0.2
Summary: Package for Multiple-criteria decision-making using TOPSIS.Requires input file,weights and impacts. Returns dataframe with score and rank of every label.This package can help improve decision-making.
Home-page: https://github.com/mitul01/topsis
Author: Mitul Tandon
Author-email: mitultandon56@gmail.com
License: MIT
Download-URL: https://github.com/mitul01/topsis/archive/v0.0.2.tar.gz
Keywords: MCDA,TOPSIS,Data Science
Platform: UNKNOWN
Classifier: Development Status :: 3 - Alpha
Classifier: Intended Audience :: Developers
Classifier: Topic :: Software Development :: Build Tools
Classifier: License :: OSI Approved :: MIT License
Classifier: Programming Language :: Python :: 3
Classifier: Programming Language :: Python :: 3.4
Classifier: Programming Language :: Python :: 3.5
Classifier: Programming Language :: Python :: 3.6
Requires-Dist: pandas
Requires-Dist: numpy
